manim_eng/__init__.py
manim_eng/_base/__init__.py
manim_eng/_base/anchor.py
manim_eng/_base/mark.py
manim_eng/_base/markable.py
manim_eng/_config/__init__.py
manim_eng/_config/config.py
manim_eng/_config/config_readers.py
manim_eng/_utils/__init__.py
manim_eng/_utils/utils.py
manim_eng/circuits/__init__.py
manim_eng/circuits/base/__init__.py
manim_eng/circuits/base/wire.py
manim_eng/circuits/circuit.py
manim_eng/circuits/voltage.py
manim_eng/circuits/wire.py
manim_eng/components/__init__.py
manim_eng/components/base/__init__.py
manim_eng/components/base/bipole.py
manim_eng/components/base/component.py
manim_eng/components/base/modifiers.py
manim_eng/components/base/monopole.py
manim_eng/components/base/source.py
manim_eng/components/base/switch.py
manim_eng/components/base/terminal.py
manim_eng/components/base/xkcd.py
manim_eng/components/capacitors.py
manim_eng/components/cells.py
manim_eng/components/diodes.py
manim_eng/components/inductors.py
manim_eng/components/monopoles.py
manim_eng/components/node.py
manim_eng/components/resistors.py
manim_eng/components/sources.py
manim_eng/components/switches.py
manim_eng/components/xkcd.py
manim_eng/implementation.py
manim_eng/logo.py
manim_eng/py.typed
manim_eng/units.py
manim_eng-0.1.0.dist-info/LICENSE
manim_eng-0.1.0.dist-info/METADATA
manim_eng-0.1.0.dist-info/WHEEL
manim_eng-0.1.0.dist-info/entry_points.txt
manim_eng-0.1.0.dist-info/RECORD
