Metadata-Version: 2.3
Name: manim-eng
Version: 0.1.0
Summary: A Manim CE plugin for drawing circuit diagrams (and other engineering diagrams in the future).
License: MIT
Keywords: manim,animation,engineering,physics,circuits
Author: overegneered
Author-email: overegneered@egneer.ing
Requires-Python: >=3.11,<3.13
Classifier: Intended Audience :: Developers
Classifier: Intended Audience :: Science/Research
Classifier: License :: OSI Approved :: MIT License
Classifier: Natural Language :: English
Classifier: Programming Language :: Python :: 3.11
Classifier: Programming Language :: Python :: 3.12
Classifier: Topic :: Multimedia :: Graphics
Classifier: Topic :: Multimedia :: Video
Classifier: Topic :: Scientific/Engineering
Classifier: Topic :: Scientific/Engineering :: Physics
Classifier: Topic :: Scientific/Engineering :: Visualization
Classifier: Typing :: Typed
Requires-Dist: manim (>=0.19,<1.0)
Project-URL: Bug tracker, https://github.com/overegneered/manim-eng/issues
Project-URL: Documentation, https://docs.manim-eng.egneer.ing
Project-URL: Repository, https://github.com/overegneered/manim-eng
